_tools.so
_mnncengine.so
.libs_tools/libgomp-f7e03b3e.so.1.0.0
.libs_tools/libz-eb09ad1d.so.1.2.3
MNN_FMA-1.0.1.dist-info/RECORD
MNN_FMA-1.0.1.dist-info/METADATA
MNN_FMA-1.0.1.dist-info/top_level.txt
MNN_FMA-1.0.1.dist-info/WHEEL
MNN_FMA-1.0.1.dist-info/entry_points.txt
MNN/__init__.py
MNN/tools/mnnquant.py
MNN/tools/mnnconvert.py
MNN/tools/mnn.py
MNN/tools/__init__.py
MNN/tools/mnnops.py
MNN/tools/mnnvisual.py
MNN/tools/mnn_fb/PadValueMode.py
MNN/tools/mnn_fb/BatchNorm.py
MNN/tools/mnn_fb/UnaryOp.py
MNN/tools/mnn_fb/Flatten.py
MNN/tools/mnn_fb/SliceTf.py
MNN/tools/mnn_fb/Reshape.py
MNN/tools/mnn_fb/LSTM.py
MNN/tools/mnn_fb/QuantizedRelu.py
MNN/tools/mnn_fb/Convolution2DCommon.py
MNN/tools/mnn_fb/PadMode.py
MNN/tools/mnn_fb/BatchMatMulParam.py
MNN/tools/mnn_fb/LRN.py
MNN/tools/mnn_fb/MatMul.py
MNN/tools/mnn_fb/OpType.py
MNN/tools/mnn_fb/Blob.py
MNN/tools/mnn_fb/RequantizationRange.py
MNN/tools/mnn_fb/DepthSpaceParam.py
MNN/tools/mnn_fb/Size.py
MNN/tools/mnn_fb/Net.py
MNN/tools/mnn_fb/OpParameter.py
MNN/tools/mnn_fb/CropAndResizeMethod.py
MNN/tools/mnn_fb/PRelu.py
MNN/tools/mnn_fb/ArgMax.py
MNN/tools/mnn_fb/ReverseSequenceParam.py
MNN/tools/mnn_fb/QuantizedConcat.py
MNN/tools/mnn_fb/AsString.py
MNN/tools/mnn_fb/OneHotParam.py
MNN/tools/mnn_fb/Relu6.py
MNN/tools/mnn_fb/DetectionOutput.py
MNN/tools/mnn_fb/QuantizedAvgPool.py
MNN/tools/mnn_fb/Relu.py
MNN/tools/mnn_fb/QuantizedAdd.py
MNN/tools/mnn_fb/DetectionPostProcessParam.py
MNN/tools/mnn_fb/PoolPadType.py
MNN/tools/mnn_fb/PackParam.py
MNN/tools/mnn_fb/FusedActivation.py
MNN/tools/mnn_fb/Usage.py
MNN/tools/mnn_fb/Normalize.py
MNN/tools/mnn_fb/QuantizedParam.py
MNN/tools/mnn_fb/ReduceJoin.py
MNN/tools/mnn_fb/GpuPipeline.py
MNN/tools/mnn_fb/GpuLibrary.py
MNN/tools/mnn_fb/ReductionType.py
MNN/tools/mnn_fb/Plugin.py
MNN/tools/mnn_fb/DataType.py
MNN/tools/mnn_fb/QuantizedSoftmax.py
MNN/tools/mnn_fb/QuantizedFloatParam.py
MNN/tools/mnn_fb/QuantizedRelu6.py
MNN/tools/mnn_fb/Convolution2D.py
MNN/tools/mnn_fb/Slice.py
MNN/tools/mnn_fb/TensorConvertInfo.py
MNN/tools/mnn_fb/BinaryOpOperation.py
MNN/tools/mnn_fb/ACCESS_TYPE.py
